{
  "success": true,
  "statistics": {
    "evaluated_validations": 1,
    "success_percent": 100.0,
    "successful_validations": 1,
    "unsuccessful_validations": 0
  },
  "validation_results": [
    {
      "success": true,
      "statistics": {
        "evaluated_expectations": 9,
        "successful_expectations": 9,
        "unsuccessful_expectations": 0,
        "success_percent": 100.0
      },
      "expectations": [
        {
          "expectation_type": "expect_column_values_to_not_be_null",
          "success": true,
          "kwargs": {
            "batch_id": "nyc_postgres-clean_yellow_trips",
            "column": "pickup_ts"
          },
          "result": {
            "element_count": 2872094,
            "unexpected_count": 0,
            "unexpected_percent": 0.0,
            "partial_unexpected_list": [],
            "partial_unexpected_counts": []
          }
        },
        {
          "expectation_type": "expect_column_values_to_not_be_null",
          "success": true,
          "kwargs": {
            "batch_id": "nyc_postgres-clean_yellow_trips",
            "column": "dropoff_ts"
          },
          "result": {
            "element_count": 2872094,
            "unexpected_count": 0,
            "unexpected_percent": 0.0,
            "partial_unexpected_list": [],
            "partial_unexpected_counts": []
          }
        },
        {
          "expectation_type": "expect_column_values_to_not_be_null",
          "success": true,
          "kwargs": {
            "batch_id": "nyc_postgres-clean_yellow_trips",
            "column": "pu_location_id"
          },
          "result": {
            "element_count": 2872094,
            "unexpected_count": 0,
            "unexpected_percent": 0.0,
            "partial_unexpected_list": [],
            "partial_unexpected_counts": []
          }
        },
        {
          "expectation_type": "expect_column_values_to_not_be_null",
          "success": true,
          "kwargs": {
            "batch_id": "nyc_postgres-clean_yellow_trips",
            "column": "do_location_id"
          },
          "result": {
            "element_count": 2872094,
            "unexpected_count": 0,
            "unexpected_percent": 0.0,
            "partial_unexpected_list": [],
            "partial_unexpected_counts": []
          }
        },
        {
          "expectation_type": "expect_column_values_to_be_between",
          "success": true,
          "kwargs": {
            "batch_id": "nyc_postgres-clean_yellow_trips",
            "column": "trip_distance",
            "min_value": 0.0
          },
          "result": {
            "element_count": 2872094,
            "unexpected_count": 0,
            "unexpected_percent": 0.0,
            "partial_unexpected_list": [],
            "missing_count": 0,
            "missing_percent": 0.0,
            "unexpected_percent_total": 0.0,
            "unexpected_percent_nonmissing": 0.0,
            "partial_unexpected_counts": []
          }
        },
        {
          "expectation_type": "expect_column_values_to_be_between",
          "success": true,
          "kwargs": {
            "batch_id": "nyc_postgres-clean_yellow_trips",
            "column": "total_amount",
            "min_value": 0.0
          },
          "result": {
            "element_count": 2872094,
            "unexpected_count": 0,
            "unexpected_percent": 0.0,
            "partial_unexpected_list": [],
            "missing_count": 0,
            "missing_percent": 0.0,
            "unexpected_percent_total": 0.0,
            "unexpected_percent_nonmissing": 0.0,
            "partial_unexpected_counts": []
          }
        },
        {
          "expectation_type": "expect_column_pair_values_a_to_be_greater_than_b",
          "success": true,
          "kwargs": {
            "batch_id": "nyc_postgres-clean_yellow_trips",
            "column_A": "dropoff_ts",
            "column_B": "pickup_ts",
            "mostly": 0.999,
            "or_equal": false,
            "ignore_row_if": "either_value_is_missing"
          },
          "result": {
            "element_count": 2872094,
            "unexpected_count": 56,
            "unexpected_percent": 0.0019497969077613756,
            "partial_unexpected_list": [
              [
                "2024-01-05T07:07:29",
                "2024-01-05T07:07:29"
              ],
              [
                "2024-01-05T13:47:06",
                "2024-01-05T13:47:06"
              ],
              [
                "2024-01-05T17:32:49",
                "2024-01-05T17:32:49"
              ],
              [
                "2024-01-06T00:27:27",
                "2024-01-06T00:27:27"
              ],
              [
                "2024-01-06T04:01:03",
                "2024-01-06T04:01:03"
              ],
              [
                "2024-01-06T21:06:06",
                "2024-01-06T21:06:06"
              ],
              [
                "2024-01-07T12:28:50",
                "2024-01-07T12:28:50"
              ],
              [
                "2024-01-08T00:07:22",
                "2024-01-08T00:07:22"
              ],
              [
                "2024-01-08T15:16:40",
                "2024-01-08T15:16:40"
              ],
              [
                "2024-01-08T20:56:17",
                "2024-01-08T20:56:17"
              ],
              [
                "2024-01-09T16:48:14",
                "2024-01-09T16:48:14"
              ],
              [
                "2024-01-09T17:40:00",
                "2024-01-09T17:40:00"
              ],
              [
                "2024-01-12T17:08:43",
                "2024-01-12T17:08:43"
              ],
              [
                "2024-01-13T00:26:55",
                "2024-01-13T00:26:55"
              ],
              [
                "2024-01-13T21:18:40",
                "2024-01-13T21:18:40"
              ],
              [
                "2024-01-13T22:10:39",
                "2024-01-13T22:10:39"
              ],
              [
                "2024-01-14T15:41:10",
                "2024-01-14T15:41:10"
              ],
              [
                "2024-01-14T22:55:53",
                "2024-01-14T22:55:53"
              ],
              [
                "2024-01-15T14:08:01",
                "2024-01-15T14:08:01"
              ],
              [
                "2024-01-15T18:18:13",
                "2024-01-15T18:18:13"
              ]
            ],
            "missing_count": 0,
            "missing_percent": 0.0,
            "unexpected_percent_total": 0.0019497969077613756,
            "unexpected_percent_nonmissing": 0.0019497969077613756,
            "partial_unexpected_counts": [
              {
                "value": [
                  "2024-01-05T07:07:29",
                  "2024-01-05T07:07:29"
                ],
                "count": 1
              },
              {
                "value": [
                  "2024-01-05T13:47:06",
                  "2024-01-05T13:47:06"
                ],
                "count": 1
              },
              {
                "value": [
                  "2024-01-05T17:32:49",
                  "2024-01-05T17:32:49"
                ],
                "count": 1
              },
              {
                "value": [
                  "2024-01-06T00:27:27",
                  "2024-01-06T00:27:27"
                ],
                "count": 1
              },
              {
                "value": [
                  "2024-01-06T04:01:03",
                  "2024-01-06T04:01:03"
                ],
                "count": 1
              },
              {
                "value": [
                  "2024-01-06T21:06:06",
                  "2024-01-06T21:06:06"
                ],
                "count": 1
              },
              {
                "value": [
                  "2024-01-07T12:28:50",
                  "2024-01-07T12:28:50"
                ],
                "count": 1
              },
              {
                "value": [
                  "2024-01-08T00:07:22",
                  "2024-01-08T00:07:22"
                ],
                "count": 1
              },
              {
                "value": [
                  "2024-01-08T15:16:40",
                  "2024-01-08T15:16:40"
                ],
                "count": 1
              },
              {
                "value": [
                  "2024-01-08T20:56:17",
                  "2024-01-08T20:56:17"
                ],
                "count": 1
              },
              {
                "value": [
                  "2024-01-09T16:48:14",
                  "2024-01-09T16:48:14"
                ],
                "count": 1
              },
              {
                "value": [
                  "2024-01-09T17:40:00",
                  "2024-01-09T17:40:00"
                ],
                "count": 1
              },
              {
                "value": [
                  "2024-01-12T17:08:43",
                  "2024-01-12T17:08:43"
                ],
                "count": 1
              },
              {
                "value": [
                  "2024-01-13T00:26:55",
                  "2024-01-13T00:26:55"
                ],
                "count": 1
              },
              {
                "value": [
                  "2024-01-13T21:18:40",
                  "2024-01-13T21:18:40"
                ],
                "count": 1
              },
              {
                "value": [
                  "2024-01-13T22:10:39",
                  "2024-01-13T22:10:39"
                ],
                "count": 1
              },
              {
                "value": [
                  "2024-01-14T15:41:10",
                  "2024-01-14T15:41:10"
                ],
                "count": 1
              },
              {
                "value": [
                  "2024-01-14T22:55:53",
                  "2024-01-14T22:55:53"
                ],
                "count": 1
              },
              {
                "value": [
                  "2024-01-15T14:08:01",
                  "2024-01-15T14:08:01"
                ],
                "count": 1
              },
              {
                "value": [
                  "2024-01-15T18:18:13",
                  "2024-01-15T18:18:13"
                ],
                "count": 1
              }
            ]
          }
        },
        {
          "expectation_type": "expect_column_values_to_be_between",
          "success": true,
          "kwargs": {
            "batch_id": "nyc_postgres-clean_yellow_trips",
            "column": "passenger_count",
            "mostly": 0.999,
            "min_value": 0.0,
            "max_value": 8.0
          },
          "result": {
            "element_count": 2872094,
            "unexpected_count": 1,
            "unexpected_percent": 3.630018364262905e-05,
            "partial_unexpected_list": [
              9.0
            ],
            "missing_count": 117287,
            "missing_percent": 4.08367553429658,
            "unexpected_percent_total": 3.481780192431028e-05,
            "unexpected_percent_nonmissing": 3.630018364262905e-05,
            "partial_unexpected_counts": [
              {
                "value": 9.0,
                "count": 1
              }
            ]
          }
        },
        {
          "expectation_type": "expect_column_values_to_be_in_set",
          "success": true,
          "kwargs": {
            "batch_id": "nyc_postgres-clean_yellow_trips",
            "column": "payment_type",
            "mostly": 0.95,
            "value_set": [
              1,
              2,
              3,
              4,
              5,
              6
            ]
          },
          "result": {
            "element_count": 2872094,
            "unexpected_count": 117287,
            "unexpected_percent": 4.08367553429658,
            "partial_unexpected_list": [
              0,
              0,
              0,
              0,
              0,
              0,
              0,
              0,
              0,
              0,
              0,
              0,
              0,
              0,
              0,
              0,
              0,
              0,
              0,
              0
            ],
            "missing_count": 0,
            "missing_percent": 0.0,
            "unexpected_percent_total": 4.08367553429658,
            "unexpected_percent_nonmissing": 4.08367553429658,
            "partial_unexpected_counts": [
              {
                "value": 0,
                "count": 20
              }
            ]
          }
        }
      ],
      "result_url": null
    }
  ]
}